user_sdk/__init__.py
user_sdk/error.py
user_sdk/test_user.py
user_sdk/user.py
sample_tryouts_12-0.0.3.dist-info/LICENCE
sample_tryouts_12-0.0.3.dist-info/METADATA
sample_tryouts_12-0.0.3.dist-info/WHEEL
sample_tryouts_12-0.0.3.dist-info/top_level.txt
sample_tryouts_12-0.0.3.dist-info/RECORD
