Metadata-Version: 2.1
Name: sample-tryouts-12
Version: 0.0.3
Summary: A small example package
Home-page: UNKNOWN
Author: Example Author
Author-email: author@example.com
License: UNKNOWN
Platform: UNKNOWN
Classifier: Programming Language :: Python :: 3
Classifier: License :: OSI Approved :: MIT License
Classifier: Operating System :: OS Independent
Requires-Dist: requests
Provides-Extra: test
Requires-Dist: pytest; extra == 'test'
Requires-Dist: pytest-runner; extra == 'test'
Requires-Dist: pytest-cov; extra == 'test'
Requires-Dist: pytest-pep8; extra == 'test'
